Tool.py
setup.py
cf666.egg-info/PKG-INFO
cf666.egg-info/SOURCES.txt
cf666.egg-info/dependency_links.txt
cf666.egg-info/top_level.txt
sztestlib/__init__.py
sztestlib/szlibone.py