Metadata-Version: 1.0
Name: cf666
Version: 1.0.0
Summary: this is a niubi lib
Home-page: UNKNOWN
Author: Sz
Author-email: 1169983240@qq.com
License: UNKNOWN
Platform: UNKNOWN
